gearup/__init__.py
gearup/config.py
gearup/meta.py
gearup/utils.py
gearup-1.0.0.dist-info/licenses/LICENSE
gearup-1.0.0.dist-info/METADATA
gearup-1.0.0.dist-info/WHEEL
gearup-1.0.0.dist-info/top_level.txt
gearup-1.0.0.dist-info/RECORD
