Metadata-Version: 2.4
Name: gearup
Version: 1.0.0
Summary: Turns Python functions into CLI via Python annotations
Author-email: Maxim Borisyak <maximus.been@gmail.com>
License: MIT License
Project-URL: Homepage, https://gitlab.com/craynn/gearup
Keywords: cli
Classifier: License :: OSI Approved :: MIT License
Classifier: Programming Language :: Python
Classifier: Programming Language :: Python :: 3
Requires-Python: >=3.9
License-File: LICENSE
Requires-Dist: omegaconf>=2.3.0
Provides-Extra: dev
Requires-Dist: pytest>=5.3.2; extra == "dev"
Dynamic: license-file
